{
  "sources": [
    {
      "title": "Release notes from osmosfeed",
      "feedUrl": "https://github.com/osmoscraft/osmosfeed/releases.atom",
      "siteUrl": "https://github.com/osmoscraft/osmosfeed/releases",
      "articles": []
    },
    {
      "title": "Schools360.in",
      "feedUrl": "https://www.schools360.in/feed/",
      "siteUrl": "https://www.schools360.in",
      "articles": [
        {
          "id": "https://www.schools360.in/?p=187653",
          "author": "Schools 360",
          "description": "PROCEEDINGS OF THE DIRECTOR, STATE COUNCIL OF EDUCATIONAL RESEARCH AND TRAINING, ANDHRA PRADESH, AMARAVATI Present : B.Pratapa Reddy, Proc..No. ESE02/187/2022SCERT Dated:17/06/2022. Sub: School Education – SCERT, AP – Training on VIII Class new textbooks – (NCERT) from 27-06-2022 to 01-07-2022 in virtual mode –Participation of teachers – Certain instructions issued. – Reg. ORDER: All the\nThe post AP SCERT Training on New 8th Class Textbooks from June 27 to July 01 appeared first on Schools360.in.",
          "link": "https://www.schools360.in/ap-scert-training-on-new-8th-class-textbooks-from-june-27-to-july-01/",
          "publishedOn": "2022-06-17T17:30:34.000Z",
          "wordCount": 943,
          "title": "AP SCERT Training on New 8th Class Textbooks from June 27 to July 01",
          "imageUrl": "https://www.schools360.in/wp-content/uploads/2020/08/apscert-textbooks.jpg"
        },
        {
          "id": "https://wordpress-625465-2031528.cloudwaysapps.com/?p=66557",
          "author": "Schools 360",
          "description": "AP SCERT 8th Class All Subjects Textbooks and Teachers Hand Guides are Available Here. So all Students who are studying Class VIII can Download the English Medium or Telugu Medium Text Books from the below links. You can Prepare for 8th Class through workbooks which will be provided here soon. Dear Students and Teachers! From\nThe post AP 8th Class Textbooks 2022-23 PDF (New) AP SCERT Class VIII EM/TM Text Books All Subjects appeared first on Schools360.in.",
          "link": "https://www.schools360.in/ap-scert-8th-class-textbooks-download-em-tm-all-subjects-pdf/",
          "publishedOn": "2022-06-17T17:26:27.000Z",
          "wordCount": 1079,
          "title": "AP 8th Class Textbooks 2022-23 PDF (New) AP SCERT Class VIII EM/TM Text Books All Subjects",
          "imageUrl": "https://www.schools360.in/wp-content/uploads/2020/09/8th-class-material.jpg"
        },
        {
          "id": "https://wordpress-625465-2031528.cloudwaysapps.com/?p=17440",
          "author": "Schools 360",
          "description": "AP POLYCET Results 2022 @ Polycetap.nic.in – AP Polycet Results, Cutoff Marks, Rank Card, Counselling 2022: Andhra Pradesh Polytechnic Entrance Exam Results are declared on June 18th, 2022 at 9.15 AM on its official site polycetap.nic.in, manabadi.com. Andhra Pradesh State Board of Technical Education training  SBTET has declared AP Polycet results 2022 on its official website Sbtet polycetap.nic.in.\nThe post AP POLYCET Results 2022 (Released) AP Polycet Rank Card Download Manabadi Polycetap.nic.in appeared first on Schools360.in.",
          "link": "https://www.schools360.in/ap-polycet-results-2022/",
          "publishedOn": "2022-06-17T17:25:02.000Z",
          "wordCount": 1341,
          "title": "AP POLYCET Results 2022 (Released) AP Polycet Rank Card Download Manabadi Polycetap.nic.in",
          "imageUrl": "https://www.schools360.in/wp-content/uploads/2018/06/ap-polycet.jpg"
        }
      ]
    },
    {
      "title": "Schools360.in",
      "feedUrl": "https://www.schools360.in/feed/",
      "siteUrl": "https://www.schools360.in",
      "articles": [
        {
          "id": "https://www.schools360.in/?p=187653",
          "author": "Schools 360",
          "description": "PROCEEDINGS OF THE DIRECTOR, STATE COUNCIL OF EDUCATIONAL RESEARCH AND TRAINING, ANDHRA PRADESH, AMARAVATI Present : B.Pratapa Reddy, Proc..No. ESE02/187/2022SCERT Dated:17/06/2022. Sub: School Education – SCERT, AP – Training on VIII Class new textbooks – (NCERT) from 27-06-2022 to 01-07-2022 in virtual mode –Participation of teachers – Certain instructions issued. – Reg. ORDER: All the\nThe post AP SCERT Training on New 8th Class Textbooks from June 27 to July 01 appeared first on Schools360.in.",
          "link": "https://www.schools360.in/ap-scert-training-on-new-8th-class-textbooks-from-june-27-to-july-01/",
          "publishedOn": "2022-06-17T17:30:34.000Z",
          "wordCount": 943,
          "title": "AP SCERT Training on New 8th Class Textbooks from June 27 to July 01",
          "imageUrl": "https://www.schools360.in/wp-content/uploads/2020/08/apscert-textbooks.jpg"
        },
        {
          "id": "https://wordpress-625465-2031528.cloudwaysapps.com/?p=66557",
          "author": "Schools 360",
          "description": "AP SCERT 8th Class All Subjects Textbooks and Teachers Hand Guides are Available Here. So all Students who are studying Class VIII can Download the English Medium or Telugu Medium Text Books from the below links. You can Prepare for 8th Class through workbooks which will be provided here soon. Dear Students and Teachers! From\nThe post AP 8th Class Textbooks 2022-23 PDF (New) AP SCERT Class VIII EM/TM Text Books All Subjects appeared first on Schools360.in.",
          "link": "https://www.schools360.in/ap-scert-8th-class-textbooks-download-em-tm-all-subjects-pdf/",
          "publishedOn": "2022-06-17T17:26:27.000Z",
          "wordCount": 1079,
          "title": "AP 8th Class Textbooks 2022-23 PDF (New) AP SCERT Class VIII EM/TM Text Books All Subjects",
          "imageUrl": "https://www.schools360.in/wp-content/uploads/2020/09/8th-class-material.jpg"
        },
        {
          "id": "https://wordpress-625465-2031528.cloudwaysapps.com/?p=17440",
          "author": "Schools 360",
          "description": "AP POLYCET Results 2022 @ Polycetap.nic.in – AP Polycet Results, Cutoff Marks, Rank Card, Counselling 2022: Andhra Pradesh Polytechnic Entrance Exam Results are declared on June 18th, 2022 at 9.15 AM on its official site polycetap.nic.in, manabadi.com. Andhra Pradesh State Board of Technical Education training  SBTET has declared AP Polycet results 2022 on its official website Sbtet polycetap.nic.in.\nThe post AP POLYCET Results 2022 (Released) AP Polycet Rank Card Download Manabadi Polycetap.nic.in appeared first on Schools360.in.",
          "link": "https://www.schools360.in/ap-polycet-results-2022/",
          "publishedOn": "2022-06-17T17:25:02.000Z",
          "wordCount": 1341,
          "title": "AP POLYCET Results 2022 (Released) AP Polycet Rank Card Download Manabadi Polycetap.nic.in",
          "imageUrl": "https://www.schools360.in/wp-content/uploads/2018/06/ap-polycet.jpg"
        }
      ]
    },
    {
      "title": "Schools360.in",
      "feedUrl": "https://www.schools360.in/feed/",
      "siteUrl": "https://www.schools360.in",
      "articles": [
        {
          "id": "https://www.schools360.in/?p=187653",
          "author": "Schools 360",
          "description": "PROCEEDINGS OF THE DIRECTOR, STATE COUNCIL OF EDUCATIONAL RESEARCH AND TRAINING, ANDHRA PRADESH, AMARAVATI Present : B.Pratapa Reddy, Proc..No. ESE02/187/2022SCERT Dated:17/06/2022. Sub: School Education – SCERT, AP – Training on VIII Class new textbooks – (NCERT) from 27-06-2022 to 01-07-2022 in virtual mode –Participation of teachers – Certain instructions issued. – Reg. ORDER: All the\nThe post AP SCERT Training on New 8th Class Textbooks from June 27 to July 01 appeared first on Schools360.in.",
          "link": "https://www.schools360.in/ap-scert-training-on-new-8th-class-textbooks-from-june-27-to-july-01/",
          "publishedOn": "2022-06-17T17:30:34.000Z",
          "wordCount": 943,
          "title": "AP SCERT Training on New 8th Class Textbooks from June 27 to July 01",
          "imageUrl": "https://www.schools360.in/wp-content/uploads/2020/08/apscert-textbooks.jpg"
        },
        {
          "id": "https://wordpress-625465-2031528.cloudwaysapps.com/?p=66557",
          "author": "Schools 360",
          "description": "AP SCERT 8th Class All Subjects Textbooks and Teachers Hand Guides are Available Here. So all Students who are studying Class VIII can Download the English Medium or Telugu Medium Text Books from the below links. You can Prepare for 8th Class through workbooks which will be provided here soon. Dear Students and Teachers! From\nThe post AP 8th Class Textbooks 2022-23 PDF (New) AP SCERT Class VIII EM/TM Text Books All Subjects appeared first on Schools360.in.",
          "link": "https://www.schools360.in/ap-scert-8th-class-textbooks-download-em-tm-all-subjects-pdf/",
          "publishedOn": "2022-06-17T17:26:27.000Z",
          "wordCount": 1079,
          "title": "AP 8th Class Textbooks 2022-23 PDF (New) AP SCERT Class VIII EM/TM Text Books All Subjects",
          "imageUrl": "https://www.schools360.in/wp-content/uploads/2020/09/8th-class-material.jpg"
        },
        {
          "id": "https://wordpress-625465-2031528.cloudwaysapps.com/?p=17440",
          "author": "Schools 360",
          "description": "AP POLYCET Results 2022 @ Polycetap.nic.in – AP Polycet Results, Cutoff Marks, Rank Card, Counselling 2022: Andhra Pradesh Polytechnic Entrance Exam Results are declared on June 18th, 2022 at 9.15 AM on its official site polycetap.nic.in, manabadi.com. Andhra Pradesh State Board of Technical Education training  SBTET has declared AP Polycet results 2022 on its official website Sbtet polycetap.nic.in.\nThe post AP POLYCET Results 2022 (Released) AP Polycet Rank Card Download Manabadi Polycetap.nic.in appeared first on Schools360.in.",
          "link": "https://www.schools360.in/ap-polycet-results-2022/",
          "publishedOn": "2022-06-17T17:25:02.000Z",
          "wordCount": 1341,
          "title": "AP POLYCET Results 2022 (Released) AP Polycet Rank Card Download Manabadi Polycetap.nic.in",
          "imageUrl": "https://www.schools360.in/wp-content/uploads/2018/06/ap-polycet.jpg"
        }
      ]
    }
  ],
  "cliVersion": "1.14.4"
}