{
  "sources": [
    {
      "title": "Release notes from osmosfeed",
      "feedUrl": "https://github.com/osmoscraft/osmosfeed/releases.atom",
      "siteUrl": "https://github.com/osmoscraft/osmosfeed/releases",
      "articles": []
    },
    {
      "title": "Schools360.in",
      "feedUrl": "https://www.schools360.in/feed/",
      "siteUrl": "https://www.schools360.in/",
      "articles": [
        {
          "id": "https://www.schools360.in/?p=182700",
          "author": "Maheshari Yerra",
          "description": "RPSC Exam Calendar 2023 pdf  आरपीएससी परीक्षा कैलेंडर has been released online. Rajasthan Public Service Commission has issued the RPSC Exam Calendar in online. So all the exam takers who are looking for the RPSC Exam Dates are able to download the RPSC Exam Calendar 2023. For Positions like School Lecturer, Junior Legal Officer, Assistant\nThe post RPSC Exam Calendar 2023 (PDF) आरपीएससी परीक्षा कैलेंडर Exam Dates appeared first on Schools360.in.",
          "link": "https://www.schools360.in/rpsc-exam-calendar/",
          "publishedOn": "2023-01-25T18:58:56.000Z",
          "wordCount": 3317,
          "title": "RPSC Exam Calendar 2023 (PDF) आरपीएससी परीक्षा कैलेंडर Exam Dates",
          "imageUrl": "https://www.schools360.in/wp-content/uploads/2019/01/RPSC.png"
        },
        {
          "id": "https://www.schools360.in/?p=195295",
          "author": "Maheshari Yerra",
          "description": "SSC CPO Admit Card 2023 for Physical Tests has been Announced on 25th January 2023. Check SSC CPO SI & CAPF’s PET Exam Date here. Staff Selection Commission is going to conduct the SSC CPO PET tests from 30th January to 4th February 2023. If you are waiting for the SSC SPO PET Admit Card\nThe post SSC CPO PET Admit Card 2022 (Out) Download Physical Test Hall Ticket appeared first on Schools360.in.",
          "link": "https://www.schools360.in/ssc-cpo-admit-card/",
          "publishedOn": "2023-01-25T18:56:49.000Z",
          "wordCount": 3383,
          "title": "SSC CPO PET Admit Card 2022 (Out) Download Physical Test Hall Ticket",
          "imageUrl": "https://www.schools360.in/wp-content/uploads/2019/09/SSC-CPO-1.jpg"
        },
        {
          "id": "https://wordpress-625465-2031528.cloudwaysapps.com/?p=16540",
          "author": "Schools 360",
          "description": "JEE Main Answer Key 2023 will be Announced soon in online form the official website @ jeemain.nta.nic.in. Check JEE Main Session 1 Exam Key, Objections here in this page. The Candidates who have appeared for the JEE Main Examination 2023 are able to Download the JEE Main Answer Key PDF From here in this page. Here\nThe post JEE Main Answer Key 2023 (Jan 25) Download Provisional Key & Response Sheet appeared first on Schools360.in.",
          "link": "https://www.schools360.in/jee-main-answer-key/",
          "publishedOn": "2023-01-25T18:38:39.000Z",
          "wordCount": 3749,
          "title": "JEE Main Answer Key 2023 (Jan 25) Download Provisional Key & Response Sheet",
          "imageUrl": "https://www.schools360.in/wp-content/uploads/2018/12/GOVT-Of-India.jpg"
        }
      ]
    },
    {
      "title": "Schools360.in",
      "feedUrl": "https://www.schools360.in/feed/",
      "siteUrl": "https://www.schools360.in/",
      "articles": [
        {
          "id": "https://www.schools360.in/?p=182700",
          "author": "Maheshari Yerra",
          "description": "RPSC Exam Calendar 2023 pdf  आरपीएससी परीक्षा कैलेंडर has been released online. Rajasthan Public Service Commission has issued the RPSC Exam Calendar in online. So all the exam takers who are looking for the RPSC Exam Dates are able to download the RPSC Exam Calendar 2023. For Positions like School Lecturer, Junior Legal Officer, Assistant\nThe post RPSC Exam Calendar 2023 (PDF) आरपीएससी परीक्षा कैलेंडर Exam Dates appeared first on Schools360.in.",
          "link": "https://www.schools360.in/rpsc-exam-calendar/",
          "publishedOn": "2023-01-25T18:58:56.000Z",
          "wordCount": 3317,
          "title": "RPSC Exam Calendar 2023 (PDF) आरपीएससी परीक्षा कैलेंडर Exam Dates",
          "imageUrl": "https://www.schools360.in/wp-content/uploads/2019/01/RPSC.png"
        },
        {
          "id": "https://www.schools360.in/?p=195295",
          "author": "Maheshari Yerra",
          "description": "SSC CPO Admit Card 2023 for Physical Tests has been Announced on 25th January 2023. Check SSC CPO SI & CAPF’s PET Exam Date here. Staff Selection Commission is going to conduct the SSC CPO PET tests from 30th January to 4th February 2023. If you are waiting for the SSC SPO PET Admit Card\nThe post SSC CPO PET Admit Card 2022 (Out) Download Physical Test Hall Ticket appeared first on Schools360.in.",
          "link": "https://www.schools360.in/ssc-cpo-admit-card/",
          "publishedOn": "2023-01-25T18:56:49.000Z",
          "wordCount": 3383,
          "title": "SSC CPO PET Admit Card 2022 (Out) Download Physical Test Hall Ticket",
          "imageUrl": "https://www.schools360.in/wp-content/uploads/2019/09/SSC-CPO-1.jpg"
        },
        {
          "id": "https://wordpress-625465-2031528.cloudwaysapps.com/?p=16540",
          "author": "Schools 360",
          "description": "JEE Main Answer Key 2023 will be Announced soon in online form the official website @ jeemain.nta.nic.in. Check JEE Main Session 1 Exam Key, Objections here in this page. The Candidates who have appeared for the JEE Main Examination 2023 are able to Download the JEE Main Answer Key PDF From here in this page. Here\nThe post JEE Main Answer Key 2023 (Jan 25) Download Provisional Key & Response Sheet appeared first on Schools360.in.",
          "link": "https://www.schools360.in/jee-main-answer-key/",
          "publishedOn": "2023-01-25T18:38:39.000Z",
          "wordCount": 3749,
          "title": "JEE Main Answer Key 2023 (Jan 25) Download Provisional Key & Response Sheet",
          "imageUrl": "https://www.schools360.in/wp-content/uploads/2018/12/GOVT-Of-India.jpg"
        }
      ]
    },
    {
      "title": "Schools360.in",
      "feedUrl": "https://www.schools360.in/feed/",
      "siteUrl": "https://www.schools360.in/",
      "articles": [
        {
          "id": "https://www.schools360.in/?p=182700",
          "author": "Maheshari Yerra",
          "description": "RPSC Exam Calendar 2023 pdf  आरपीएससी परीक्षा कैलेंडर has been released online. Rajasthan Public Service Commission has issued the RPSC Exam Calendar in online. So all the exam takers who are looking for the RPSC Exam Dates are able to download the RPSC Exam Calendar 2023. For Positions like School Lecturer, Junior Legal Officer, Assistant\nThe post RPSC Exam Calendar 2023 (PDF) आरपीएससी परीक्षा कैलेंडर Exam Dates appeared first on Schools360.in.",
          "link": "https://www.schools360.in/rpsc-exam-calendar/",
          "publishedOn": "2023-01-25T18:58:56.000Z",
          "wordCount": 3317,
          "title": "RPSC Exam Calendar 2023 (PDF) आरपीएससी परीक्षा कैलेंडर Exam Dates",
          "imageUrl": "https://www.schools360.in/wp-content/uploads/2019/01/RPSC.png"
        },
        {
          "id": "https://www.schools360.in/?p=195295",
          "author": "Maheshari Yerra",
          "description": "SSC CPO Admit Card 2023 for Physical Tests has been Announced on 25th January 2023. Check SSC CPO SI & CAPF’s PET Exam Date here. Staff Selection Commission is going to conduct the SSC CPO PET tests from 30th January to 4th February 2023. If you are waiting for the SSC SPO PET Admit Card\nThe post SSC CPO PET Admit Card 2022 (Out) Download Physical Test Hall Ticket appeared first on Schools360.in.",
          "link": "https://www.schools360.in/ssc-cpo-admit-card/",
          "publishedOn": "2023-01-25T18:56:49.000Z",
          "wordCount": 3383,
          "title": "SSC CPO PET Admit Card 2022 (Out) Download Physical Test Hall Ticket",
          "imageUrl": "https://www.schools360.in/wp-content/uploads/2019/09/SSC-CPO-1.jpg"
        },
        {
          "id": "https://wordpress-625465-2031528.cloudwaysapps.com/?p=16540",
          "author": "Schools 360",
          "description": "JEE Main Answer Key 2023 will be Announced soon in online form the official website @ jeemain.nta.nic.in. Check JEE Main Session 1 Exam Key, Objections here in this page. The Candidates who have appeared for the JEE Main Examination 2023 are able to Download the JEE Main Answer Key PDF From here in this page. Here\nThe post JEE Main Answer Key 2023 (Jan 25) Download Provisional Key & Response Sheet appeared first on Schools360.in.",
          "link": "https://www.schools360.in/jee-main-answer-key/",
          "publishedOn": "2023-01-25T18:38:39.000Z",
          "wordCount": 3749,
          "title": "JEE Main Answer Key 2023 (Jan 25) Download Provisional Key & Response Sheet",
          "imageUrl": "https://www.schools360.in/wp-content/uploads/2018/12/GOVT-Of-India.jpg"
        }
      ]
    }
  ],
  "cliVersion": "1.15.1"
}