{
  "sources": [
    {
      "title": "Release notes from osmosfeed",
      "feedUrl": "https://github.com/osmoscraft/osmosfeed/releases.atom",
      "siteUrl": "https://github.com/osmoscraft/osmosfeed/releases",
      "articles": []
    },
    {
      "title": "Schools360.in",
      "feedUrl": "https://www.schools360.in/feed/",
      "siteUrl": "https://www.schools360.in/",
      "articles": [
        {
          "id": "https://wordpress-625465-2031528.cloudwaysapps.com/?p=52653",
          "author": "Schools 360",
          "description": "NITTTR Chandigarh Nursery Teachers (NTT) Online Form 2024: Director, School Education Department, Chandigarh Administration has advertised the latest employment notification noticeable as NITTTR Chandigarh Recruitment 2024 with thorough details. The organization invites Online employment forms from eligible and competent job\nThe post NITTTR Chandigarh NTT Recruitment 2024 Apply 100 Nursery Teacher Vacancy appeared first on Schools360.in.",
          "link": "https://www.schools360.in/nitttr-chandigarh-ntt-recruitment/",
          "publishedOn": "2023-12-29T17:51:45.000Z",
          "wordCount": 2265,
          "title": "NITTTR Chandigarh NTT Recruitment 2024 Apply 100 Nursery Teacher Vacancy",
          "imageUrl": "https://www.schools360.in/wp-content/uploads/2019/02/NITTTR.png"
        },
        {
          "id": "https://wordpress-625465-2031528.cloudwaysapps.com/?p=33426",
          "author": "Schools 360",
          "description": "JKBOSE Class 11 Result 2023 Released: The Jammu & Kashmir Board of School Education (JKBOSE) has released the bi-annual result for class 11th private examination candidates today, 29 December 2023.  JKBOSE Class 11 Jammu Division Bi-Annual 2023 Result Direct Link\nThe post JKBOSE Class 11th Result 2023 (OUT) Bi-Annual Private Exam Results appeared first on Schools360.in.",
          "link": "https://www.schools360.in/jkbose-class-11th-results-jammu/",
          "publishedOn": "2023-12-29T17:44:49.000Z",
          "wordCount": 2337,
          "title": "JKBOSE Class 11th Result 2023 (OUT) Bi-Annual Private Exam Results",
          "imageUrl": "https://www.schools360.in/wp-content/uploads/2020/02/JKBOSE-Results.jpg"
        },
        {
          "id": "https://www.schools360.in/?p=216513",
          "author": "Schools 360",
          "description": "தமிழ் நாடு ஊரகப் பகுதி மாணவர்களுக்கான திறனாய்வுத் தேர்வு (TRUST), டிசம்பர் 2023 விடைக்குறிப்பு பொருள்: அரசுத் தேர்வுகள் இயக்ககம், சென்னை-6 – தமிழ் நாடு ஊரகப் பகுதி மாணவர்களுக்கான திறனாய்வுத் தேர்வு (TRUST), டிசம்பர் 2023- விடைக்குறிப்பு (Tentative Key Answer) – இணையதளத்தில் வெளியிடுதல் – தொடர்பாக. ****** 16.12.2023 அன்று நடைபெற்ற\nThe post TRUST Examination Dec 2023 Answer Key விடைக்குறிப்பு PDF appeared first on Schools360.in.",
          "link": "https://www.schools360.in/trust-examination-answer-key/",
          "publishedOn": "2023-12-29T17:23:23.000Z",
          "wordCount": 1797,
          "title": "TRUST Examination Dec 2023 Answer Key விடைக்குறிப்பு PDF",
          "imageUrl": "https://www.schools360.in/wp-content/uploads/2023/11/answer-key.jpg"
        }
      ]
    },
    {
      "title": "Schools360.in",
      "feedUrl": "https://www.schools360.in/feed/",
      "siteUrl": "https://www.schools360.in/",
      "articles": [
        {
          "id": "https://wordpress-625465-2031528.cloudwaysapps.com/?p=52653",
          "author": "Schools 360",
          "description": "NITTTR Chandigarh Nursery Teachers (NTT) Online Form 2024: Director, School Education Department, Chandigarh Administration has advertised the latest employment notification noticeable as NITTTR Chandigarh Recruitment 2024 with thorough details. The organization invites Online employment forms from eligible and competent job\nThe post NITTTR Chandigarh NTT Recruitment 2024 Apply 100 Nursery Teacher Vacancy appeared first on Schools360.in.",
          "link": "https://www.schools360.in/nitttr-chandigarh-ntt-recruitment/",
          "publishedOn": "2023-12-29T17:51:45.000Z",
          "wordCount": 2265,
          "title": "NITTTR Chandigarh NTT Recruitment 2024 Apply 100 Nursery Teacher Vacancy",
          "imageUrl": "https://www.schools360.in/wp-content/uploads/2019/02/NITTTR.png"
        },
        {
          "id": "https://wordpress-625465-2031528.cloudwaysapps.com/?p=33426",
          "author": "Schools 360",
          "description": "JKBOSE Class 11 Result 2023 Released: The Jammu & Kashmir Board of School Education (JKBOSE) has released the bi-annual result for class 11th private examination candidates today, 29 December 2023.  JKBOSE Class 11 Jammu Division Bi-Annual 2023 Result Direct Link\nThe post JKBOSE Class 11th Result 2023 (OUT) Bi-Annual Private Exam Results appeared first on Schools360.in.",
          "link": "https://www.schools360.in/jkbose-class-11th-results-jammu/",
          "publishedOn": "2023-12-29T17:44:49.000Z",
          "wordCount": 2337,
          "title": "JKBOSE Class 11th Result 2023 (OUT) Bi-Annual Private Exam Results",
          "imageUrl": "https://www.schools360.in/wp-content/uploads/2020/02/JKBOSE-Results.jpg"
        },
        {
          "id": "https://www.schools360.in/?p=216513",
          "author": "Schools 360",
          "description": "தமிழ் நாடு ஊரகப் பகுதி மாணவர்களுக்கான திறனாய்வுத் தேர்வு (TRUST), டிசம்பர் 2023 விடைக்குறிப்பு பொருள்: அரசுத் தேர்வுகள் இயக்ககம், சென்னை-6 – தமிழ் நாடு ஊரகப் பகுதி மாணவர்களுக்கான திறனாய்வுத் தேர்வு (TRUST), டிசம்பர் 2023- விடைக்குறிப்பு (Tentative Key Answer) – இணையதளத்தில் வெளியிடுதல் – தொடர்பாக. ****** 16.12.2023 அன்று நடைபெற்ற\nThe post TRUST Examination Dec 2023 Answer Key விடைக்குறிப்பு PDF appeared first on Schools360.in.",
          "link": "https://www.schools360.in/trust-examination-answer-key/",
          "publishedOn": "2023-12-29T17:23:23.000Z",
          "wordCount": 1797,
          "title": "TRUST Examination Dec 2023 Answer Key விடைக்குறிப்பு PDF",
          "imageUrl": "https://www.schools360.in/wp-content/uploads/2023/11/answer-key.jpg"
        }
      ]
    },
    {
      "title": "Schools360.in",
      "feedUrl": "https://www.schools360.in/feed/",
      "siteUrl": "https://www.schools360.in/",
      "articles": [
        {
          "id": "https://wordpress-625465-2031528.cloudwaysapps.com/?p=52653",
          "author": "Schools 360",
          "description": "NITTTR Chandigarh Nursery Teachers (NTT) Online Form 2024: Director, School Education Department, Chandigarh Administration has advertised the latest employment notification noticeable as NITTTR Chandigarh Recruitment 2024 with thorough details. The organization invites Online employment forms from eligible and competent job\nThe post NITTTR Chandigarh NTT Recruitment 2024 Apply 100 Nursery Teacher Vacancy appeared first on Schools360.in.",
          "link": "https://www.schools360.in/nitttr-chandigarh-ntt-recruitment/",
          "publishedOn": "2023-12-29T17:51:45.000Z",
          "wordCount": 2265,
          "title": "NITTTR Chandigarh NTT Recruitment 2024 Apply 100 Nursery Teacher Vacancy",
          "imageUrl": "https://www.schools360.in/wp-content/uploads/2019/02/NITTTR.png"
        },
        {
          "id": "https://wordpress-625465-2031528.cloudwaysapps.com/?p=33426",
          "author": "Schools 360",
          "description": "JKBOSE Class 11 Result 2023 Released: The Jammu & Kashmir Board of School Education (JKBOSE) has released the bi-annual result for class 11th private examination candidates today, 29 December 2023.  JKBOSE Class 11 Jammu Division Bi-Annual 2023 Result Direct Link\nThe post JKBOSE Class 11th Result 2023 (OUT) Bi-Annual Private Exam Results appeared first on Schools360.in.",
          "link": "https://www.schools360.in/jkbose-class-11th-results-jammu/",
          "publishedOn": "2023-12-29T17:44:49.000Z",
          "wordCount": 2337,
          "title": "JKBOSE Class 11th Result 2023 (OUT) Bi-Annual Private Exam Results",
          "imageUrl": "https://www.schools360.in/wp-content/uploads/2020/02/JKBOSE-Results.jpg"
        },
        {
          "id": "https://www.schools360.in/?p=216513",
          "author": "Schools 360",
          "description": "தமிழ் நாடு ஊரகப் பகுதி மாணவர்களுக்கான திறனாய்வுத் தேர்வு (TRUST), டிசம்பர் 2023 விடைக்குறிப்பு பொருள்: அரசுத் தேர்வுகள் இயக்ககம், சென்னை-6 – தமிழ் நாடு ஊரகப் பகுதி மாணவர்களுக்கான திறனாய்வுத் தேர்வு (TRUST), டிசம்பர் 2023- விடைக்குறிப்பு (Tentative Key Answer) – இணையதளத்தில் வெளியிடுதல் – தொடர்பாக. ****** 16.12.2023 அன்று நடைபெற்ற\nThe post TRUST Examination Dec 2023 Answer Key விடைக்குறிப்பு PDF appeared first on Schools360.in.",
          "link": "https://www.schools360.in/trust-examination-answer-key/",
          "publishedOn": "2023-12-29T17:23:23.000Z",
          "wordCount": 1797,
          "title": "TRUST Examination Dec 2023 Answer Key விடைக்குறிப்பு PDF",
          "imageUrl": "https://www.schools360.in/wp-content/uploads/2023/11/answer-key.jpg"
        }
      ]
    }
  ],
  "cliVersion": "1.15.1"
}